pykitcommander/__init__.py
pykitcommander/firmwareinterface.py
pykitcommander/kitcommandererrors.py
pykitcommander/kitmanager.py
pykitcommander/kitprotocols.py
pykitcommander/programmer.py
pykitcommander/fw/avr/atmega4808-aws-iot-demo.hex
pykitcommander/fw/avr/atmega4808-google-iot-demo.hex
pykitcommander/fw/avr/atmega4808-iot-provision-v2.hex
pykitcommander/fw/avr/atmega4808-iot-winc-upgrade.hex
pykitcommander/fw/avr/avr128db48-iot-cellular-mini-arduino-demo.hex
pykitcommander/fw/avr/avr128db48-iot-cellular-mini-provisioning.hex
pykitcommander/fw/avr/avr128db64-iot-cellular-provision.hex
pykitcommander/fw/pic/AzureIotPnpDps.X.production.hex
pykitcommander/fw/pic/pic24fj128ga705-aws-iot-demo.hex
pykitcommander/fw/pic/pic24fj128ga705-google-iot-demo.hex
pykitcommander/fw/pic/pic24fj128ga705-iot-provision-v2.hex
pykitcommander/fw/pic/pic24fj128ga705-iot-winc-upgrade.hex
pykitcommander/fw/sam/AzureIotPnpDps.X.production.hex
pykitcommander/fw/sam/sam_d21_iot_wg.X.production.hex
pykitcommander/fw/sam/samd21e18a-trustplatform-provision.hex
pykitcommander/fw/sam/samd21g18a-iot-provision.hex
pykitcommander/fw/sam/samd21g18a-iot-winc-upgrade.hex
pykitcommander/fw/sam/samd21g18a-iot-wx-provision.hex
pykitcommander/fw/sam/samd21g18a-iot-wx-winc-upgrade.hex
pykitcommander/picpack/pic24fj128ga705/nedbg_pic24fj128ga705.py
pykitcommander/picpack/pic24fj128ga705/pic24fj128ga705pds.py
pykitcommander/picpack/pic24fj128ga705/common/__init__.py
pykitcommander/picpack/pic24fj128ga705/common/debuggerbase.py
pykitcommander/picpack/pic24fj128ga705/common/debuginterfaceprovider.py
pykitcommander/picpack/pic24fj128ga705/common/debugprovider.py
pykitcommander/picpack/pic24fj128ga705/common/gen4engineinterface.py
pykitcommander/picpack/pic24fj128ga705/common/gen4scriptwrapper.py
pykitcommander/picpack/pic24fj128ga705/common/icspio.py
pykitcommander/picpack/pic24fj128ga705/common/logging.json
pykitcommander/picpack/pic24fj128ga705/common/mplablog.py
pykitcommander-2.8.3.18.dist-info/LICENSE.txt
pykitcommander-2.8.3.18.dist-info/METADATA
pykitcommander-2.8.3.18.dist-info/WHEEL
pykitcommander-2.8.3.18.dist-info/top_level.txt
pykitcommander-2.8.3.18.dist-info/RECORD
