Metadata-Version: 2.1
Name: pykitcommander
Version: 2.8.3.18
Summary: Collection of tools for cloud provisioning of Microchip IoT kits
Author-email: Microchip Technology <support@microchip.com>
License: MIT
Project-URL: Homepage, https://github.com/microchip-pic-avr-tools/pykitcommander
Keywords: Microchip,AVR,PIC,AVR-IoT,PIC-IoT
Classifier: Development Status :: 5 - Production/Stable
Classifier: Intended Audience :: Developers
Classifier: Topic :: Software Development :: Embedded Systems
Classifier: Programming Language :: Python :: 3
Classifier: Programming Language :: Python :: 3.8
Classifier: Programming Language :: Python :: 3.9
Classifier: Programming Language :: Python :: 3.10
Classifier: Programming Language :: Python :: 3.11
Classifier: Operating System :: Microsoft :: Windows
Classifier: Operating System :: POSIX :: Linux
Classifier: Operating System :: MacOS
Classifier: License :: OSI Approved :: MIT License
Requires-Python: >=3.8
License-File: LICENSE.txt
Requires-Dist: pyserial
Requires-Dist: hexdump
Requires-Dist: pyedbglib >=2.22
Requires-Dist: pymcuprog >=3.3
Requires-Dist: pydebuggerconfig >=3.5
Provides-Extra: dev
Requires-Dist: pylint >=2.15 ; extra == 'dev'
Provides-Extra: doc
Requires-Dist: mock ; extra == 'doc'
Requires-Dist: sphinx ; extra == 'doc'
Provides-Extra: test
Requires-Dist: mock ; extra == 'test'
Requires-Dist: pytest ; extra == 'test'
